yamager/__init__.py
yamager/yamager.py
yamager-1.1.1.dist-info/LICENSE
yamager-1.1.1.dist-info/METADATA
yamager-1.1.1.dist-info/WHEEL
yamager-1.1.1.dist-info/top_level.txt
yamager-1.1.1.dist-info/RECORD
