Metadata-Version: 2.1
Name: yamager
Version: 1.1.1
Summary: Yamager - Simple module for parsing images from Yandex and Google.
Home-page: https://github.com/DedInc/yamager
Author: Maehdakvan
Author-email: visitanimation@google.com
Project-URL: Bug Tracker, https://github.com/DedInc/yamager/issues
Classifier: Programming Language :: Python :: 3
Classifier: License :: OSI Approved :: MIT License
Classifier: Operating System :: OS Independent
Requires-Python: >=3.6
License-File: LICENSE
Requires-Dist: requests
Requires-Dist: lxml
